anchor/__init__.py
anchor/_http.py
anchor/anchor.py
anchor/config.py
anchor/exceptions.py
anchor/models.py
anchor/telemetry.py
anchor/integrations/__init__.py
anchor/integrations/crewai.py
anchor/integrations/langchain.py
anchor/integrations/mem0.py
anchor/namespaces/__init__.py
anchor/namespaces/agents.py
anchor/namespaces/audit.py
anchor/namespaces/base.py
anchor/namespaces/checkpoints.py
anchor/namespaces/config.py
anchor/namespaces/data.py
anchorai-1.0.1.dist-info/licenses/LICENSE
anchorai-1.0.1.dist-info/METADATA
anchorai-1.0.1.dist-info/WHEEL
anchorai-1.0.1.dist-info/top_level.txt
anchorai-1.0.1.dist-info/RECORD
