Metadata-Version: 2.4
Name: anchorai
Version: 1.0.1
Summary: Control what your AI agents store. Audit everything.
Author-email: Tasha Kim <founders@getanchor.dev>
License-Expression: Apache-2.0
Project-URL: Homepage, https://getanchor.dev
Project-URL: Documentation, https://docs.getanchor.dev
Project-URL: Repository, https://github.com/anchorco/anchor-sdk
Project-URL: Issues, https://github.com/anchorco/anchor-sdk/issues
Keywords: ai,agents,ai-agents,storage,policy,audit,governance,llm,langchain,crewai,openai,sdk,agent-memory,state,checkpoints
Classifier: Development Status :: 5 - Production/Stable
Classifier: Intended Audience :: Developers
Classifier: Topic :: Software Development :: Libraries :: Python Modules
Classifier: Topic :: Scientific/Engineering :: Artificial Intelligence
Classifier: Programming Language :: Python :: 3
Classifier: Programming Language :: Python :: 3.8
Classifier: Programming Language :: Python :: 3.9
Classifier: Programming Language :: Python :: 3.10
Classifier: Programming Language :: Python :: 3.11
Classifier: Programming Language :: Python :: 3.12
Requires-Python: >=3.8
License-File: LICENSE
Requires-Dist: requests>=2.28.0
Requires-Dist: pydantic>=2.0.0
Provides-Extra: langchain
Requires-Dist: langchain>=0.1.0; extra == "langchain"
Provides-Extra: crewai
Requires-Dist: crewai>=0.1.0; extra == "crewai"
Provides-Extra: mem0
Requires-Dist: mem0ai>=0.1.0; extra == "mem0"
Provides-Extra: all
Requires-Dist: langchain>=0.1.0; extra == "all"
Requires-Dist: crewai>=0.1.0; extra == "all"
Requires-Dist: mem0ai>=0.1.0; extra == "all"
Provides-Extra: dev
Requires-Dist: pytest>=7.0.0; extra == "dev"
Requires-Dist: pytest-cov>=4.0.0; extra == "dev"
Requires-Dist: black>=23.0.0; extra == "dev"
Requires-Dist: mypy>=1.0.0; extra == "dev"
Requires-Dist: ruff>=0.1.0; extra == "dev"
Dynamic: license-file
